remotable_function/__init__.py
remotable_function/client_unified.py
remotable_function/config.py
remotable_function/gateway_unified.py
remotable_function/py.typed
remotable_function/client/__init__.py
remotable_function/client/client.py
remotable_function/client/tool.py
remotable_function/client/tools/__init__.py
remotable_function/client/tools/filesystem.py
remotable_function/client/tools/shell.py
remotable_function/core/__init__.py
remotable_function/core/auth.py
remotable_function/core/cache.py
remotable_function/core/compression.py
remotable_function/core/events.py
remotable_function/core/exceptions.py
remotable_function/core/protocol.py
remotable_function/core/ratelimit.py
remotable_function/core/registry.py
remotable_function/core/types.py
remotable_function/core/validation.py
remotable_function/server/__init__.py
remotable_function/server/manager.py
remotable_function-2.0.0.dist-info/licenses/LICENSE
remotable_function-2.0.0.dist-info/METADATA
remotable_function-2.0.0.dist-info/WHEEL
remotable_function-2.0.0.dist-info/top_level.txt
remotable_function-2.0.0.dist-info/RECORD
