Metadata-Version: 2.4
Name: remotable-function
Version: 2.0.0
Summary: Simple and efficient RPC framework for AI agents
Author: Remotable Function Contributors
License-Expression: MIT
Project-URL: Homepage, https://github.com/StarAniseStudio/remotable-function
Project-URL: Documentation, https://github.com/StarAniseStudio/remotable-function/blob/main/README.md
Project-URL: Repository, https://github.com/StarAniseStudio/remotable-function
Project-URL: Issues, https://github.com/StarAniseStudio/remotable-function/issues
Keywords: rpc,websocket,json-rpc,remote-procedure-call,client-server,tools,agent,automation
Classifier: Development Status :: 4 - Beta
Classifier: Intended Audience :: Developers
Classifier: Topic :: Software Development :: Libraries :: Python Modules
Classifier: Topic :: System :: Networking
Classifier: Topic :: System :: Distributed Computing
Classifier: Programming Language :: Python :: 3
Classifier: Programming Language :: Python :: 3.8
Classifier: Programming Language :: Python :: 3.9
Classifier: Programming Language :: Python :: 3.10
Classifier: Programming Language :: Python :: 3.11
Classifier: Programming Language :: Python :: 3.12
Classifier: Programming Language :: Python :: 3.13
Classifier: Operating System :: OS Independent
Classifier: Typing :: Typed
Requires-Python: >=3.8
License-File: LICENSE
Requires-Dist: websockets>=10.0
Requires-Dist: aiofiles>=23.0
Provides-Extra: dev
Requires-Dist: pytest>=7.0; extra == "dev"
Requires-Dist: pytest-asyncio>=0.20; extra == "dev"
Requires-Dist: black>=22.0; extra == "dev"
Requires-Dist: mypy>=1.0; extra == "dev"
Dynamic: license-file
